mcp_psilo_mock/__init__.py
mcp_psilo_mock/__main__.py
mcp_psilo_mock/fake_psilo_data.csv
mcp_psilo_mock/server_stdio.py
mcp_psilo_mock-0.1.19.dist-info/METADATA
mcp_psilo_mock-0.1.19.dist-info/WHEEL
mcp_psilo_mock-0.1.19.dist-info/top_level.txt
mcp_psilo_mock-0.1.19.dist-info/RECORD
