Metadata-Version: 2.4
Name: mcp-psilo-mock
Version: 0.1.19
Summary: Mock MCP server tools for psilo model context protocol
Home-page: https://gitlab.nimbus.amgen.com/xai/mcp_psilo
Author: Kyle Fang
Author-email: kfang01@amgen.com
Requires-Python: >=3.7
Requires-Dist: fastapi
Requires-Dist: pandas
Requires-Dist: mcp
Dynamic: author
Dynamic: author-email
Dynamic: description
Dynamic: description-content-type
Dynamic: home-page
Dynamic: requires-dist
Dynamic: requires-python
Dynamic: summary
